nake_src/__init__.py
nake_src/main.py
nake-0.0.3.dist-info/LICENSE
nake-0.0.3.dist-info/METADATA
nake-0.0.3.dist-info/WHEEL
nake-0.0.3.dist-info/entry_points.txt
nake-0.0.3.dist-info/top_level.txt
nake-0.0.3.dist-info/RECORD
