Metadata-Version: 2.1
Name: nake
Version: 0.0.3
Summary: nifty nool for nunning scripts
Home-page: UNKNOWN
Author: Hubert "Koshmaar" Rutkowski
Author-email: do.not@email.me
License: MIT
Platform: UNKNOWN
Classifier: Programming Language :: Python :: 3
Classifier: Operating System :: OS Independent
Classifier: License :: OSI Approved :: MIT License
Classifier: Development Status :: 3 - Alpha
Classifier: Intended Audience :: Information Technology
Requires-Python: >=3.5.0
